setup.py
duy_train_package/__init__.py
duy_train_package/main.py
duy_train_package/predict.py
duy_train_package/process_data.py
duy_train_package/train.py
duy_train_package/train_model.py
duy_train_package.egg-info/PKG-INFO
duy_train_package.egg-info/SOURCES.txt
duy_train_package.egg-info/dependency_links.txt
duy_train_package.egg-info/top_level.txt