Metadata-Version: 2.1
Name: duy-train-package
Version: 0.2
Summary: No description
Home-page: https://github.com/HoangDuy09042001/TrainModelPackage.git
Author: Duy
Author-email: hoangtanduynx@gmail.com
